utms/__init__.py
utms/__main__.py
utms/ai.py
utms/anchors.py
utms/cli/__init__.py
utms/cli/commands/anchor/__init__.py
utms/cli/commands/anchor/get.py
utms/cli/commands/anchor/list.py
utms/cli/commands/clock/__init__.py
utms/cli/commands/clock/clock.py
utms/cli/commands/config/__init__.py
utms/cli/commands/config/get.py
utms/cli/commands/config/list.py
utms/cli/commands/config/set.py
utms/cli/commands/core/__init__.py
utms/cli/commands/core/command.py
utms/cli/commands/core/command_manager.py
utms/cli/commands/core/hierarchy.py
utms/cli/commands/daytime/__init__.py
utms/cli/commands/daytime/convert.py
utms/cli/commands/daytime/timetable.py
utms/cli/commands/resolve/__init__.py
utms/cli/commands/resolve/resolve.py
utms/cli/commands/unit/__init__.py
utms/cli/commands/unit/convert.py
utms/cli/commands/unit/list.py
utms/cli/commands/unit/table.py
utms/cli/shell.py
utms/clock.py
utms/config.py
utms/constants.py
utms/resources/anchors.json
utms/resources/clock.png
utms/resources/config.json
utms/resources/system_prompt.txt
utms/units.py
utms/utils.py
utms-0.1.10.dist-info/LICENSE
utms-0.1.10.dist-info/METADATA
utms-0.1.10.dist-info/WHEEL
utms-0.1.10.dist-info/entry_points.txt
utms-0.1.10.dist-info/RECORD
