Metadata-Version: 2.3
Name: utms
Version: 0.1.10
Summary: Universal Time Measurement System
Home-page: https://github.com/danielonsecurity/utms
License: GPL-3.0-or-later
Keywords: time,utms,time-tracking,universal-time-measurement-system,python,clock
Author: Daniel Neagaru
Author-email: daniel@neagaru.com
Requires-Python: >=3.10
Classifier: Development Status :: 1 - Planning
Classifier: Environment :: Console
Classifier: Framework :: Pytest
Classifier: Framework :: tox
Classifier: Intended Audience :: Developers
Classifier: Intended Audience :: Education
Classifier: Intended Audience :: End Users/Desktop
Classifier: Intended Audience :: Information Technology
Classifier: Intended Audience :: Science/Research
Classifier: Intended Audience :: System Administrators
Classifier: License :: OSI Approved :: GNU General Public License v3 or later (GPLv3+)
Classifier: Natural Language :: English
Classifier: Operating System :: OS Independent
Classifier: Programming Language :: Python
Classifier: Programming Language :: Python :: 3
Classifier: Programming Language :: Python :: 3.10
Classifier: Programming Language :: Python :: 3.11
Classifier: Programming Language :: Python :: 3.12
Classifier: Programming Language :: Python :: 3.13
Classifier: Programming Language :: Python :: 3 :: Only
Classifier: Topic :: Internet :: WWW/HTTP
Classifier: Topic :: Office/Business :: Scheduling
Classifier: Topic :: Scientific/Engineering :: Artificial Intelligence
Classifier: Topic :: Scientific/Engineering :: Physics
Classifier: Topic :: Sociology :: History
Classifier: Topic :: Software Development :: Libraries :: Python Modules
Classifier: Topic :: Software Development :: Testing
Classifier: Topic :: System :: Networking :: Time Synchronization
Classifier: Topic :: Utilities
Requires-Dist: appdirs (>=1.4.4,<2.0.0)
Requires-Dist: black (>=24.10.0,<25.0.0)
Requires-Dist: colorama (>=0.4.6,<0.5.0)
Requires-Dist: dateparser (>=1.2.0,<2.0.0)
Requires-Dist: google-generativeai (>=0.8.3,<0.9.0)
Requires-Dist: importlib-metadata (>=8.5.0,<9.0.0)
Requires-Dist: ntplib (>=0.4.0,<0.5.0)
Requires-Dist: pillow (>=11.0.0,<12.0.0)
Requires-Dist: prettytable (>=3.12.0,<4.0.0)
Requires-Dist: prompt-toolkit (>=3.0.48,<4.0.0)
Requires-Dist: python-dotenv (>=1.0.1,<2.0.0)
Project-URL: Documentation, https://github.com/danielonsecurity/utms
Project-URL: Repository, https://github.com/danielonsecurity/utms
